{
	// Misc
	"Loading advertisement":"Cargando publicidad",
	"Select a Contact":"Selecciona un Contacto",
	
	// Menus
	"Preferences":"Preferencias",
	"Help":"Ayuda",
	"Edit":"Editar",
	
	// List
	"Contacts":"Contactos",
	
	// Edit Contact
	"Phone":"Teléfono",
	"Email":"Correo electrónico",
	"IM":"IM",
	"SMS":"SMS",
	"Save":"Guardar",
	"Cancel":"Cancelar",
	"Delete":"Borrar",
	"Auto Select":"Auto-Seleccionar",
	"No Selection":"Sin Selección",
	"None Available":"Ninguno Disponible",
	"Home":"Casa",
	"Personal":"Personal",
	"Work":"Trabajo",
	"Other":"Otro",
	"Mobile":"Móvil",
	"Pager":"Buscapersonas",
	"Personal fax":"Fax Personal",
	"Work Fax":"Fax de Trabajo",
	"Main":"Principal",
	"SIM":"SIM",
	
	// Preferences
	"General Preferences":"Preferencias Generales",
	"Contact Preferences":"Preferencias de Contacto",
	"Auto-Dial Phone":"Auto-Marcacion",
	"Yes":"Sí",
	"No":"No",
	"Contact Name Position":"Posición del Nombre",
	"Top":"Parte Superior",
	"Bottom":"Parte Inferior",
	"Hidden":"Oculto",
	"Allow Display Rotation":"Permitir Rotación",
	"Launcher Icon":"Icono del Lanzador",
	"Default":"Predeterminado",
	"Theme":"Tema",
	"Blue Steel":"Acero Azul",
	"Spring":"Primavera",
	"Start Up View":"Vista de Inicio",
	"Grid":"Cuadricula",
	"List":"Lista"
}